[{"data":"4th February 2023 09:17:15","author":"log","text":"asfasf","status":"active"},{"data":"4th February 2023 09:17:17","author":"log","text":"sagagsag","status":"active"},{"data":"4th February 2023 09:17:18","author":"log","text":"gadgaga","status":"active"},{"data":"5th February 2023 10:47:58","author":"log","text":"sdasdsadd"},{"data":"5th February 2023 10:56:16","author":"log","text":"sdasdsadd"},{"data":"5th February 2023 10:59:11","author":"log","text":"sdasdsadd"},{"data":"5th February 2023 10:59:22","author":"log","text":"sdasdsadd"},{"data":"5th February 2023 10:59:43","author":"log","text":"sgsg"}]